acasio9/__init__.py
acasio9-0.0.1.dist-info/LICENCE.txt
acasio9-0.0.1.dist-info/METADATA
acasio9-0.0.1.dist-info/WHEEL
acasio9-0.0.1.dist-info/top_level.txt
acasio9-0.0.1.dist-info/RECORD
