Metadata-Version: 2.1
Name: acasio9
Version: 0.0.1
Summary: Advanced Calculator
Home-page: 
Author: Adarsh Gangwar
Author-email: adarsh.phy22@gmail.com
License: MIT
Keywords: calculator
Classifier: Development Status :: 5 - Production/Stable
Classifier: Intended Audience :: Education
Classifier: Operating System :: Microsoft :: Windows :: Windows 10
Classifier: License :: OSI Approved :: MIT License
Classifier: Programming Language :: Python :: 3
License-File: LICENCE.txt
